mifastboot/__init__.py
mifastboot/__main__.py
mifastboot/cli.py
mifastboot/core.py
mifastboot/worker.py
mifastboot-1.0.0a2.dist-info/METADATA
mifastboot-1.0.0a2.dist-info/WHEEL
mifastboot-1.0.0a2.dist-info/entry_points.txt
mifastboot-1.0.0a2.dist-info/top_level.txt
mifastboot-1.0.0a2.dist-info/RECORD
