Metadata-Version: 2.4
Name: mifastboot
Version: 1.0.0a2
Requires-Python: >=3.6
Requires-Dist: pyusb
